intervalcron/__init__.py
intervalcron/intervalcron.py
apscheduler_intervalcron-0.2.0.dist-info/LICENSE
apscheduler_intervalcron-0.2.0.dist-info/METADATA
apscheduler_intervalcron-0.2.0.dist-info/WHEEL
apscheduler_intervalcron-0.2.0.dist-info/entry_points.txt
apscheduler_intervalcron-0.2.0.dist-info/top_level.txt
apscheduler_intervalcron-0.2.0.dist-info/RECORD
