Metadata-Version: 2.1
Name: apscheduler-intervalcron
Version: 0.2.0
Summary: Interval Cron Trigger Plugin for APScheduler
Home-page: https://github.com/Code0987/apscheduler-intervalcron
Author: Neeraj
Author-email: durgapalneeraj@gmail.com
License: MIT
Keywords: apscheduler,interval,cron
Platform: UNKNOWN
Classifier: Development Status :: 3 - Alpha
Classifier: Intended Audience :: Developers
Classifier: License :: OSI Approved :: MIT License
Classifier: Programming Language :: Python :: 3
Classifier: Programming Language :: Python :: 3.4
Classifier: Programming Language :: Python :: 3.5
Classifier: Programming Language :: Python :: 3.6
Classifier: Programming Language :: Python :: 3.7
Requires-Dist: apscheduler
Requires-Dist: python-dateutil
